pleenok/analysis/conformance.py
pleenok/analysis/simulation.py
pleenok/catalog/from_internet.py
pleenok/catalog/from_papers.py
pleenok/conversion/adtool.py
pleenok/conversion/graphviz.py
pleenok/conversion/process_tree.py
pleenok/conversion/risqflan.py
pleenok/model/attack_tree.py
pleenok/utils/log_utils.py
pleenok-0.0.2.dist-info/METADATA
pleenok-0.0.2.dist-info/WHEEL
pleenok-0.0.2.dist-info/top_level.txt
pleenok-0.0.2.dist-info/RECORD
