Metadata-Version: 2.1
Name: pleenok
Version: 0.0.2
Summary: Attack Trees and Process Mining
Author: Andrea Burattin
License: Apache-2.0
Requires-Dist: pm4py ~=2.7.12.4
Requires-Dist: graphviz ~=0.20.3
Requires-Dist: pandas ~=2.2.3
